<?xml version="1.0" encoding="UTF-8"?>
<Document id="45426" nome_arquivo="https_DOISpont__baraduplas_www.ufrgs.brbarraprogespbarrawp-contentbarrauploadsbarraDocumentosOficiaisbarraBoletinsbarra2019barraBOLETIM-Nº-02-18.01.2019.pdf" site="https://www.ufrgs.br/progesp/wp-content/uploads/DocumentosOficiais/Boletins/2019/BOLETIM-Nº-02-18.01.2019.pdf"><portaria ID="02" data="PORTARIA Nº 02 JANEIRO 2019"><text>PORTARIA Nº 02 DE 11 DE JANEIRO DE 2019 ,  ,  , A VICE-DIRETORA DO INSTITUTO DE FILOSOFIA CIÊNCIAS , HUMANAS DA UNIVERSIDADE FEDERAL DO RIO GRANDE DO SUL, no uso , de suas atribuições legais, ,  ,  , RESOLVE: ,  ,  , PRORROGAR a Comissão Disciplinar Discente, pelo prazo de , trinta (30) dias, composta pelos Professores Alfredo Alejandro Gugliano e , Ricardo Antonio Cavalcanti Schiel mais o Aluno Vinícius Porcher Alós, sob , a presidência do primeiro, apurar os fatos constantes no processo nº , 23078.007542/2018-42. ,  ,  , Profa. Maria Izabel Noll , Vice-Diretora ,  ,  , PORTARIA Nº 01 DE 17 DE JANEIRO DE 2019 ,  ,  , A Vice-Diretora da Faculdade de Biblioteconomia e Comunicação, , em exercício da Direção, no uso de suas atribuições, de acordo com o art. 12, , §2º, da Resolução nº 07/2004 do CEPE/UFRGS,  ,  ,  , RESOLVE ,  ,  , Designar os professores RENE FAUSTINO GABRIEL JUNIOR , (presidente) e MARCIA REGINA BERTOTTO, lotados e em exercício no , 2 , Departamento de Ciência da Informação, e a discente AMANDA DALL´AGNOL , BARBOSA, para compor a Comissão Disciplinar Discente, para, no prazo de 30 , (trinta) dias, apurar os fatos denunciados no processo nº 23078.000252/2019-, 59. ,  ,  , Profa. Ilza Maria Tourinho Girardi, , Vice-Diretora da FABICO ,  ,  , PORTARIA Nº 003 DE 17 DE JANEIRO DE 2019 ,  ,  , A DIRETORA DA ESCOLA DE ENFERMAGEM DA , UNIVERSIDADE FEDERAL DO RIO GRANDE DO SUL, no uso de suas , atribuições legais, ,  ,  , RESOLVE: ,  ,  , REINSTAURAR PROCESSO DISCIPLINAR DISCENTE, nos , autos do processo nº 23078.023341/2017-10, reconduzindo a Comissão , designada pela Portaria nº 085, de 18 de dezembro de 2017, publicada no , Boletim de Atos Oficiais PROGESP/UFRGS nº 69/2017, edição de 28.12.17, , alterada pela Portaria nº 001 de 02.01.2018, publicada no Boletim de Atos , Oficiais PROGESP/UFRGS nº 01/2018, edição de 03.01.2018, para que sejam , finalizados os trabalhos dessa comissão. A presente portaria entrará em vigor a , partir da data de sua publicação no Boletim de Atos Oficiais desta , Universidade. ,  ,  , Profa. Dra. GISELA MARIA SCHEBELLA SOUTO DE MOURA , Diretora da Escola de Enfermagem da UFRGS </text></portaria><portaria ID="597" data="PORTARIA Nº 597 JANEIRO 2019"><text>PORTARIA Nº 597 DE 18 DE JANEIRO DE 2019 ,  ,  , O PRÓ-REITOR DE GESTÃO DE PESSOAS DA , UNIVERSIDADE FEDERAL DO RIO GRANDE DO SUL, no uso de suas , atribuições, considerando o disposto na Portaria nº 7904, de 05 de outubro de , 2016  ,  ,  , RESOLVE  ,  ,  , REINSTAURAR a SINDICÂNCIA INVESTIGATIVA reconduzindo , a Comissão integrada pelos servidores designados pela Portaria nº , 10401/2018, de 21 de dezembro de 2018, publicada no Boletim de Atos Oficiais , 3 , PROGESP/UFRGS nº 60/2018, edição de 21.12.2018, para que, no prazo de , 60 (sessenta) dias, seja dado andamento aos trabalhos da Comissão , Sindicante. A presente portaria entrará em vigor a partir da data de sua , publicação no Boletim de Atos Oficiais desta Universidade. Processo nº , 23078.012716/2018-99. ,  ,  , MAURÍCIO VIÉGAS DA SILVA , Pró-Reitor de Gestão de Pessoas </text></portaria></Document>
